pytest_django_liveserver_ssl/__init__.py
pytest_django_liveserver_ssl/__main__.py
pytest_django_liveserver_ssl/_types.py
pytest_django_liveserver_ssl/fixtures.py
pytest_django_liveserver_ssl/helpers.py
pytest_django_liveserver_ssl/live_server_ssl_helper.py
pytest_django_liveserver_ssl/plugin.py
pytest_django_liveserver_ssl/ssl_certificate.py
pytest_django_liveserver_ssl-0.0.3.dist-info/LICENSE
pytest_django_liveserver_ssl-0.0.3.dist-info/METADATA
pytest_django_liveserver_ssl-0.0.3.dist-info/WHEEL
pytest_django_liveserver_ssl-0.0.3.dist-info/entry_points.txt
pytest_django_liveserver_ssl-0.0.3.dist-info/top_level.txt
pytest_django_liveserver_ssl-0.0.3.dist-info/RECORD
